requests_scitokens/__init__.py
requests_scitokens/_version.py
requests_scitokens/auth.py
requests_scitokens/requests.py
requests_scitokens/sessions.py
requests_scitokens/utils.py
requests_scitokens/tests/__init__.py
requests_scitokens/tests/conftest.py
requests_scitokens/tests/test_auth.py
requests_scitokens/tests/test_utils.py
requests_scitokens-0.2.1.dist-info/licenses/LICENSE
requests_scitokens-0.2.1.dist-info/METADATA
requests_scitokens-0.2.1.dist-info/WHEEL
requests_scitokens-0.2.1.dist-info/top_level.txt
requests_scitokens-0.2.1.dist-info/RECORD
