Metadata-Version: 2.4
Name: requests-scitokens
Version: 0.2.1
Summary: A requests plugin for SciToken authorisation
Author-email: Duncan Macleod <macleoddm@cardiff.ac.uk>
License: Apache-2.0
Project-URL: Bug Tracker, https://git.ligo.org/computing/software/requests-scitokens/-/issues
Project-URL: Documentation, https://requests-scitokens.readthedocs.io/
Project-URL: Source Code, https://git.ligo.org/computing/software/requests-scitokens.git
Classifier: Development Status :: 4 - Beta
Classifier: License :: OSI Approved :: Apache Software License
Classifier: Operating System :: OS Independent
Classifier: Programming Language :: Python
Classifier: Programming Language :: Python :: 3
Classifier: Programming Language :: Python :: 3.9
Classifier: Programming Language :: Python :: 3.10
Classifier: Programming Language :: Python :: 3.11
Classifier: Programming Language :: Python :: 3.12
Classifier: Programming Language :: Python :: 3.13
Classifier: Topic :: Scientific/Engineering
Requires-Python: >=3.9
License-File: LICENSE
Requires-Dist: requests>=2.32.0
Requires-Dist: scitokens>=1.8
Provides-Extra: test
Requires-Dist: pytest>=3.1.0; extra == "test"
Requires-Dist: pytest-cov>=2.4.0; extra == "test"
Requires-Dist: requests-mock; extra == "test"
Provides-Extra: docs
Requires-Dist: furo; extra == "docs"
Requires-Dist: sphinx; extra == "docs"
Requires-Dist: sphinx-automodapi; extra == "docs"
Requires-Dist: sphinx-copybutton; extra == "docs"
Requires-Dist: sphinx-design; extra == "docs"
Dynamic: license-file
